{
  "barrel_season_w": 2.071,
  "barrel_l8d_w": 0.977,
  "la_season_w": 1.352,
  "la_l8d_w": 2.084,
  "ev_season_w": 0.92,
  "ev_l8d_w": 2.061,
  "iso_season_w": 1.857,
  "iso_vs_hand_w": 2.5,
  "hard_hit_season_w": 1.87,
  "hard_hit_l8d_w": 1.205,
  "xwoba_l8d_w": 0.3,
  "xslg_l8d_w": 1.682,
  "bat_speed_l8d_w": 2.346,
  "slg_l8d_w": 1.758,
  "xslg_gap_l8d_w": 0.985,
  "l8d_hr_w": 1.089,
  "fb_pct_season_w": 1.0,
  "pull_pct_season_w": 0.949,
  "k_pct_l8d_w": 1.417,
  "hot_cold_mult_w": 0.908,
  "pit_hr9_season_w": 0.679,
  "pit_hr9_vs_hand_w": 1.216,
  "pit_slg_season_w": 1.0,
  "pit_slg_vs_hand_w": 0.726,
  "pit_hard_hit_w": 1.158,
  "pit_fb_pct_w": 1.0,
  "pit_era_diff_w": 0.592,
  "pit_k9_season_w": 0.972,
  "park_w": 0.982,
  "weather_w": 1.096,
  "bullpen_w": 1.806,
  "bat_platoon_w": 0.55,
  "pit_platoon_w": 1.101,
  "pitch_delta_w": 1.167,
  "k_pct_w": 1.046,
  "chase_rate_w": 1.0,
  "pit_stuff_plus_w": 1.0,
  "active_stats": [
    "xslg_l8d",
    "pull_pct_season",
    "iso_season",
    "barrel_pct_season",
    "pit_hard_hit_season",
    "ev_l8d",
    "xwoba_l8d",
    "k_pct_l8d"
  ],
  "last_calibrated": "2026-04-29",
  "records_used": 2071,
  "calibration_round": 45,
  "promoted_stats": [],
  "dropped_stats": [],
  "recent_changes": [],
  "all_correlations": {
    "iso_vs_hand": 0.4317,
    "bat_speed_l8d": 0.3873,
    "xwoba_l8d": -0.3747,
    "la_l8d": 0.312,
    "barrel_season": 0.3081,
    "ev_l8d": 0.3054,
    "hard_hit_season": 0.2502,
    "iso_season": 0.2465,
    "bullpen": 0.2319,
    "slg_l8d": 0.218,
    "xslg_l8d": 0.1963,
    "bat_platoon": -0.1296,
    "k_pct_l8d": 0.12,
    "pit_era_diff": -0.1175,
    "la_season": 0.1013,
    "pit_hr9_season": -0.0922,
    "pit_slg_vs_hand": -0.0788,
    "pit_hr9_vs_hand": 0.0622,
    "hard_hit_l8d": 0.0589,
    "pitch_delta": 0.0481,
    "pit_hard_hit": 0.0455,
    "weather": 0.0275,
    "ev_season": -0.0231,
    "pull_pct_season": -0.0148,
    "pit_k9_season": -0.0079,
    "barrel_l8d": -0.0065,
    "park": -0.0053
  },
  "model_type": "decision_tree",
  "tree_depth": 5,
  "tree_min_leaf": 35,
  "tree_n_leaves": 14,
  "feature_importances": {
    "xslg_l8d": 0.3225,
    "pull_pct_season": 0.2057,
    "iso_season": 0.1699,
    "barrel_pct_season": 0.1092,
    "pit_hard_hit_season": 0.0641,
    "ev_l8d": 0.063,
    "xwoba_l8d": 0.0395,
    "k_pct_l8d": 0.0261
  },
  "feature_medians": {
    "barrel_pct_season": 10.2,
    "hard_hit_season": 42.9,
    "ev_season": 89.8,
    "iso_season": 0.162,
    "la_season": 14.0,
    "pull_pct_season": 40.3,
    "barrel_pct_l8d": 7.5,
    "hard_hit_l8d": 27.3,
    "ev_l8d": 83.7,
    "bat_speed_l8d": 70.2,
    "xwoba_l8d": 0.385,
    "xslg_l8d": 0.549,
    "slg_l8d": 0.419,
    "iso_l8d": 0.173,
    "k_pct_l8d": 21.9,
    "la_l8d": 17.9,
    "iso_vs_hand": 0.17,
    "slg_vs_hand": 0.4,
    "pit_hr9_season": 0.96,
    "pit_era_season": 3.67,
    "pit_hard_hit_season": 40.6,
    "pit_k9_season": 8.6,
    "pit_hr9_vs_hand": 0.84,
    "pit_slg_vs_hand": 0.36,
    "park_factor": 1.04,
    "weather_mult": 1.0,
    "bullpen_hr9": 1.11,
    "bat_platoon_mult": 0.94,
    "pit_platoon_mult": 1.06,
    "pitch_matchup_score": 0.36
  },
  "hr_rates_at_leaves": [
    0.0,
    0.0,
    0.0,
    0.0,
    22.6,
    35.8,
    37.2,
    47.7,
    49.1,
    49.4,
    59.9,
    64.0,
    73.4,
    78.3
  ],
  "tree_hr_rate": 13.7,
  "calibration_factor": 0.5072,
  "next_depth_upgrade": 2500
}